{
  "scene_id": "mixed_urban_01",
  "name": "Mixed Urban Intersection",
  "description": "Urban intersection with vehicles, pedestrians, and cyclists",
  "pointsBin": "assets/scenes/mixed_urban_01/mixed_urban_01_100k.bin",
  "pointCount": 100000,
  "pointStride": 3,
  "bounds": {
    "min": [
      -45,
      -45,
      -2
    ],
    "max": [
      45,
      45,
      12
    ]
  },
  "ground_truth": [
    {
      "id": "f748eded-bd68-440f-ad99-2a23c1992d58",
      "class": "vehicle",
      "center": [
        11.347527223472028,
        -38.28553043556846,
        -1.2
      ],
      "dimensions": {
        "width": 1.801994139041524,
        "length": 4.502310397419806,
        "height": 1.7504853192006102
      },
      "yaw": 2.4162298471677515,
      "confidence": 0.8562750774703988
    },
    {
      "id": "cf62d2f5-ab7c-42e2-8f57-d92925748df8",
      "class": "vehicle",
      "center": [
        3.9443488648724667,
        -3.7553455462689413,
        -1.2
      ],
      "dimensions": {
        "width": 1.8472479047907098,
        "length": 4.156492444586686,
        "height": 1.5650075375396848
      },
      "yaw": 0.8706373759873092,
      "confidence": 0.9145012884726919
    },
    {
      "id": "502ce6f0-b41c-497b-a573-4daeae952c78",
      "class": "vehicle",
      "center": [
        -38.90236904727317,
        33.53103054290577,
        -1.2
      ],
      "dimensions": {
        "width": 1.9145362916420003,
        "length": 4.17466605394979,
        "height": 1.5012706110567418
      },
      "yaw": 0.9861794457013167,
      "confidence": 0.8911237656567753
    },
    {
      "id": "55541910-8239-47cf-b9c5-360af1249a1e",
      "class": "vehicle",
      "center": [
        36.737747301184214,
        -4.464346052829399,
        -1.2
      ],
      "dimensions": {
        "width": 1.7297303600688605,
        "length": 4.819690221642174,
        "height": 1.6978356473708782
      },
      "yaw": 2.6909105297540483,
      "confidence": 0.8953632379753006
    },
    {
      "id": "b06e3373-865e-4339-ab96-bf651775e3f3",
      "class": "vehicle",
      "center": [
        27.74400793065348,
        -8.773789106089076,
        -1.2
      ],
      "dimensions": {
        "width": 1.6052452907783668,
        "length": 4.345705654573935,
        "height": 1.4623900644878403
      },
      "yaw": 2.7154070780649064,
      "confidence": 0.8555059965660676
    },
    {
      "id": "cefce78c-3613-4f11-b10b-874e7a28fc62",
      "class": "vehicle",
      "center": [
        5.880172879315637,
        -18.83985544154024,
        -1.2
      ],
      "dimensions": {
        "width": 1.6371589553885244,
        "length": 4.608456946788492,
        "height": 1.694890698919631
      },
      "yaw": -2.1987644655922143,
      "confidence": 0.9495267302751343
    },
    {
      "id": "a8e293b2-37f6-4c3f-98e2-65d87e198331",
      "class": "vehicle",
      "center": [
        -28.515929897954013,
        -21.060256493092115,
        -1.2
      ],
      "dimensions": {
        "width": 1.6777299481647627,
        "length": 4.709575142948833,
        "height": 1.795131515149785
      },
      "yaw": 2.1129309200582176,
      "confidence": 0.8703985319848911
    },
    {
      "id": "df6c6072-fdca-4f12-8e0d-dbaeddfb2de0",
      "class": "vehicle",
      "center": [
        -14.559038550213472,
        -6.815965565584321,
        -1.2
      ],
      "dimensions": {
        "width": 1.9231226424839984,
        "length": 4.223792268760157,
        "height": 1.6601984174926023
      },
      "yaw": -1.2130905692247458,
      "confidence": 0.9035011500519099
    },
    {
      "id": "75254858-009f-40b6-bdf0-055d36cb2734",
      "class": "pedestrian",
      "center": [
        -17.069063451555042,
        -4.864076775052837,
        -1.1
      ],
      "dimensions": {
        "width": 0.5452444558368011,
        "length": 0.5979444076491357,
        "height": 1.6315913675506304
      },
      "yaw": 1.0333015667638907,
      "confidence": 0.8359808838816628
    },
    {
      "id": "559aabf5-5294-42cf-9b28-e33b5594af1a",
      "class": "pedestrian",
      "center": [
        9.63836739527791,
        11.021181674737534,
        -1.1
      ],
      "dimensions": {
        "width": 0.6735877724653259,
        "length": 0.5812099480118456,
        "height": 1.7125268576405401
      },
      "yaw": -1.2159558950919145,
      "confidence": 0.8826606024688424
    },
    {
      "id": "944a3c8e-d056-41ee-8c54-d4f9beb7a34f",
      "class": "pedestrian",
      "center": [
        -28.08952801677563,
        -27.60693162664662,
        -1.1
      ],
      "dimensions": {
        "width": 0.6091811309045554,
        "length": 0.5250308400107468,
        "height": 1.7738833219007173
      },
      "yaw": 1.2587646583983672,
      "confidence": 0.8404064964662085
    },
    {
      "id": "e0c4e73f-4dc2-421d-b24e-bf052babc45b",
      "class": "pedestrian",
      "center": [
        -30.59535003245661,
        -3.786679081758244,
        -1.1
      ],
      "dimensions": {
        "width": 0.5758207843967854,
        "length": 0.5890637255938709,
        "height": 1.804758487947712
      },
      "yaw": -2.21959565492231,
      "confidence": 0.8927002005957263
    },
    {
      "id": "e74116bf-b73f-469c-bb0e-858c3c79bd56",
      "class": "pedestrian",
      "center": [
        -5.303684367740367,
        5.84211713237157,
        -1.1
      ],
      "dimensions": {
        "width": 0.6519870103138881,
        "length": 0.5456413605727087,
        "height": 1.8264528608665835
      },
      "yaw": 0.8201175773581193,
      "confidence": 0.9168074104743266
    },
    {
      "id": "e128f1d9-2aaf-4c8a-9e8f-f5a0385cf912",
      "class": "pedestrian",
      "center": [
        -18.011947121325086,
        12.309388505551972,
        -1.1
      ],
      "dimensions": {
        "width": 0.6116450876121106,
        "length": 0.6553047400469431,
        "height": 1.7797850709645753
      },
      "yaw": 0.03347867999410292,
      "confidence": 0.9633613094096815
    },
    {
      "id": "0fba6f58-2e94-4f90-b4aa-9317e6f8d862",
      "class": "pedestrian",
      "center": [
        18.657069075220463,
        -19.066218089843016,
        -1.1
      ],
      "dimensions": {
        "width": 0.5172338223756011,
        "length": 0.5256334172555115,
        "height": 1.7984874603226455
      },
      "yaw": -1.2542340341170042,
      "confidence": 0.8723894069705327
    },
    {
      "id": "128c0ac3-6c75-46c7-afbe-1187abd87c7a",
      "class": "pedestrian",
      "center": [
        29.257769616886137,
        0.04294553557839009,
        -1.1
      ],
      "dimensions": {
        "width": 0.5767701198766448,
        "length": 0.6713344627213257,
        "height": 1.847670896886014
      },
      "yaw": -1.7945050567142322,
      "confidence": 0.9511025262847101
    },
    {
      "id": "339f6b01-7a75-4b96-b587-fba0fb195c42",
      "class": "pedestrian",
      "center": [
        20.169073891866347,
        2.67468577341009,
        -1.1
      ],
      "dimensions": {
        "width": 0.5436589729149209,
        "length": 0.5442254432067829,
        "height": 1.6387048172832979
      },
      "yaw": 2.514034951871716,
      "confidence": 0.861148327152133
    },
    {
      "id": "2b71a09c-0a96-4a11-a11b-2c031ed4a051",
      "class": "pedestrian",
      "center": [
        19.300382290002126,
        6.792033232004982,
        -1.1
      ],
      "dimensions": {
        "width": 0.550844703271579,
        "length": 0.6065685086716393,
        "height": 1.7903115832625571
      },
      "yaw": -1.0033334537608556,
      "confidence": 0.9348183428899386
    },
    {
      "id": "ceb99340-552a-4599-9c8b-58ebba394829",
      "class": "cyclist",
      "center": [
        32.04621499145209,
        39.286446283783405,
        -1
      ],
      "dimensions": {
        "width": 0.7826137008292389,
        "length": 1.8201470846203305,
        "height": 1.7420923687073755
      },
      "yaw": -2.3465283281080778,
      "confidence": 0.926906725678702
    },
    {
      "id": "07945f82-67e7-4103-915c-5bd39c3d1ee5",
      "class": "cyclist",
      "center": [
        -32.081215043784326,
        -32.008439017264735,
        -1
      ],
      "dimensions": {
        "width": 0.6568737574812744,
        "length": 1.645550250075868,
        "height": 1.6013981923318652
      },
      "yaw": 2.9808518917122395,
      "confidence": 0.7563621532398549
    },
    {
      "id": "fc838a49-120e-4ac4-adac-b76958f05799",
      "class": "cyclist",
      "center": [
        25.90941319340665,
        -19.188552750803655,
        -1
      ],
      "dimensions": {
        "width": 0.6412019907948308,
        "length": 1.7455732484897575,
        "height": 1.7850226078480638
      },
      "yaw": -0.6636811669842486,
      "confidence": 0.8381702728867378
    },
    {
      "id": "2b5e2a86-e5aa-4d0d-83c4-9e1efcfc2cba",
      "class": "cyclist",
      "center": [
        -16.28884418297435,
        38.41252855132565,
        -1
      ],
      "dimensions": {
        "width": 0.7400479330309058,
        "length": 1.663299541421882,
        "height": 1.7249506975227809
      },
      "yaw": -0.28270047605377124,
      "confidence": 0.7922514971799631
    }
  ],
  "predictions": {
    "DSVT_Voxel": [
      {
        "id": "396d11e8-706a-4284-8fa7-453fe3d0bd09",
        "class": "vehicle",
        "center": [
          17.3146073598409,
          11.256413476679569,
          -1.2
        ],
        "dimensions": {
          "width": 1.8541386935477864,
          "length": 4.679157932983999,
          "height": 1.7655546617804259
        },
        "yaw": 2.432717203028801,
        "confidence": 0.8157623544674014
      },
      {
        "id": "e789d13f-6127-4e24-b4a1-9ab2b73ef0f8",
        "class": "vehicle",
        "center": [
          33.154817407013596,
          -31.0300018899307,
          -1.2
        ],
        "dimensions": {
          "width": 1.9054727176528357,
          "length": 4.93275537434601,
          "height": 1.601839002295275
        },
        "yaw": 1.0181960583113154,
        "confidence": 0.8479263963383652
      },
      {
        "id": "54c2bae3-fd2c-4168-8180-16a868b1e57c",
        "class": "vehicle",
        "center": [
          -39.01838570407193,
          -18.80449739799472,
          -1.2
        ],
        "dimensions": {
          "width": 1.9894124377155478,
          "length": 4.982347280517044,
          "height": 1.4949665662869693
        },
        "yaw": -2.8898903712656443,
        "confidence": 0.8089520207849445
      },
      {
        "id": "f15923a7-8051-49b9-909f-d8121e882b86",
        "class": "vehicle",
        "center": [
          9.166578755290224,
          32.350979907888416,
          -1.2
        ],
        "dimensions": {
          "width": 1.9656232154339894,
          "length": 4.918090450340342,
          "height": 1.6998175019589916
        },
        "yaw": 0.35437416999282556,
        "confidence": 0.8449739735396852
      },
      {
        "id": "4a830a42-25ad-4b57-9c4d-b061977cd7cb",
        "class": "vehicle",
        "center": [
          -27.16903353544671,
          -39.33154514629352,
          -1.2
        ],
        "dimensions": {
          "width": 1.7112086020415713,
          "length": 4.73700844945282,
          "height": 1.5557976529390598
        },
        "yaw": -2.5338405653152836,
        "confidence": 0.8604364120820593
      },
      {
        "id": "506439ed-fa09-4280-b021-b05eeea068b4",
        "class": "vehicle",
        "center": [
          -29.404088796010353,
          -38.233553093919994,
          -1.2
        ],
        "dimensions": {
          "width": 1.7297528012230763,
          "length": 4.18066173445973,
          "height": 1.5989900116691005
        },
        "yaw": 0.15631686728246086,
        "confidence": 0.9355377069751197
      },
      {
        "id": "8ebe8150-8210-4eeb-86f1-135a76748449",
        "class": "vehicle",
        "center": [
          -20.50718392567637,
          3.3359064863537924,
          -1.2
        ],
        "dimensions": {
          "width": 1.6700062558068025,
          "length": 4.283147803560678,
          "height": 1.6712740319171393
        },
        "yaw": 2.175867288311771,
        "confidence": 0.8968372078844954
      },
      {
        "id": "f63c3cb9-a5f6-48dc-9a7d-c15978b7e6a4",
        "class": "vehicle",
        "center": [
          38.85932996256243,
          28.091577563198257,
          -1.2
        ],
        "dimensions": {
          "width": 1.9500915895580804,
          "length": 4.4129209892684225,
          "height": 1.6831773393799823
        },
        "yaw": 1.8612505640206525,
        "confidence": 0.939557136761167
      },
      {
        "id": "45fd0a06-5aa5-4497-82cd-693af59bc91c",
        "class": "pedestrian",
        "center": [
          6.32905372384716,
          41.22783594204883,
          -1.1
        ],
        "dimensions": {
          "width": 0.5424645511624298,
          "length": 0.5321601604843014,
          "height": 1.7290604354983636
        },
        "yaw": -1.2164348641133347,
        "confidence": 0.779834722187898
      },
      {
        "id": "4b37dc8e-d968-43d8-a3d9-46a0d3747622",
        "class": "pedestrian",
        "center": [
          22.080578855777432,
          21.016529408614858,
          -1.1
        ],
        "dimensions": {
          "width": 0.5023369429429357,
          "length": 0.6963789767758483,
          "height": 1.8439116836045277
        },
        "yaw": 2.910395947776675,
        "confidence": 0.9000185230748687
      },
      {
        "id": "7052b63e-060d-44b6-bee1-114929420858",
        "class": "pedestrian",
        "center": [
          8.654299839375753,
          1.5424395616538646,
          -1.1
        ],
        "dimensions": {
          "width": 0.5980289787227774,
          "length": 0.5279226983258961,
          "height": 1.6854128014406329
        },
        "yaw": -0.09855297799614338,
        "confidence": 0.9070901299489356
      },
      {
        "id": "1be6abf1-6b96-4b05-bd74-70ef871d45c7",
        "class": "pedestrian",
        "center": [
          -29.02551464256733,
          15.233106539559529,
          -1.1
        ],
        "dimensions": {
          "width": 0.6987691993525267,
          "length": 0.6988374156614667,
          "height": 1.6743998080437463
        },
        "yaw": -2.2569526829667597,
        "confidence": 0.797510341101492
      },
      {
        "id": "6f7abe0d-f406-4521-b8c6-b95eeda24cc4",
        "class": "pedestrian",
        "center": [
          -9.764363395368562,
          21.412700154386954,
          -1.1
        ],
        "dimensions": {
          "width": 0.6644988790026907,
          "length": 0.6903389601567891,
          "height": 1.8052155419990783
        },
        "yaw": 0.4187533031623989,
        "confidence": 0.8520823255251977
      },
      {
        "id": "c8fb4f0f-dd81-45f1-b209-551e0b753806",
        "class": "pedestrian",
        "center": [
          -7.406474565946837,
          37.25783390749088,
          -1.1
        ],
        "dimensions": {
          "width": 0.664418562262723,
          "length": 0.6372184175296669,
          "height": 1.73246548111155
        },
        "yaw": -0.5287078557211404,
        "confidence": 0.7709477320271596
      },
      {
        "id": "eec64189-55e8-49b8-89e5-20ee7f099800",
        "class": "pedestrian",
        "center": [
          37.64804607441552,
          13.953538165809164,
          -1.1
        ],
        "dimensions": {
          "width": 0.6169053029483992,
          "length": 0.600419896527888,
          "height": 1.8279762025393909
        },
        "yaw": -2.6645924301873416,
        "confidence": 0.7887943661956027
      },
      {
        "id": "4ae5cd74-8642-4d01-95e0-0702a46bdb6f",
        "class": "pedestrian",
        "center": [
          -3.9457803342225546,
          40.17770158668506,
          -1.1
        ],
        "dimensions": {
          "width": 0.5421173265382656,
          "length": 0.5491596934023666,
          "height": 1.7724170366704641
        },
        "yaw": 1.7208532659981488,
        "confidence": 0.7783056711491282
      },
      {
        "id": "d00b3fe0-3dfb-4b0a-a9a2-aa2200283405",
        "class": "pedestrian",
        "center": [
          -11.496786186930372,
          -27.699618014309777,
          -1.1
        ],
        "dimensions": {
          "width": 0.52177358675528,
          "length": 0.6619354718431256,
          "height": 1.7208708490431648
        },
        "yaw": 0.6572135311496305,
        "confidence": 0.7614954665650506
      },
      {
        "id": "cbe54d92-ec73-4f54-831b-db1f33464b0e",
        "class": "pedestrian",
        "center": [
          -17.585214734971036,
          2.3486215281891916,
          -1.1
        ],
        "dimensions": {
          "width": 0.6418375604639772,
          "length": 0.5403365851212373,
          "height": 1.7329393701222089
        },
        "yaw": 3.082047739139984,
        "confidence": 0.7751752802300919
      },
      {
        "id": "605c5855-8df2-4357-a514-5dcabfbd69e1",
        "class": "cyclist",
        "center": [
          23.88573459561765,
          -4.938298842216774,
          -1
        ],
        "dimensions": {
          "width": 0.7951000049640337,
          "length": 1.6003754210626437,
          "height": 1.6250760281403143
        },
        "yaw": -2.1446624085789243,
        "confidence": 0.8009256395732983
      },
      {
        "id": "2885637f-0510-40c7-b003-b8871883327c",
        "class": "cyclist",
        "center": [
          -17.872802329505557,
          -21.361302657102,
          -1
        ],
        "dimensions": {
          "width": 0.7526376435321918,
          "length": 1.780684474643903,
          "height": 1.65596120645573
        },
        "yaw": -1.7677870866807914,
        "confidence": 0.8077057117990701
      },
      {
        "id": "6ac9a3d3-8940-4cec-838d-08e685611156",
        "class": "cyclist",
        "center": [
          40.58655390851278,
          28.307381633893982,
          -1
        ],
        "dimensions": {
          "width": 0.7003344220105165,
          "length": 1.7697264946506361,
          "height": 1.6928221559585757
        },
        "yaw": -2.632897549114441,
        "confidence": 0.7992875316458561
      },
      {
        "id": "7df24600-fa4d-4062-b79c-8818c83a6b48",
        "class": "cyclist",
        "center": [
          24.03888705229545,
          -20.653287139371784,
          -1
        ],
        "dimensions": {
          "width": 0.6891444197919234,
          "length": 1.6756265439219589,
          "height": 1.6003535556497046
        },
        "yaw": -2.1610168548788833,
        "confidence": 0.8598731917127922
      }
    ],
    "AGILE3D_CP_Pillar_032": [
      {
        "id": "f3d69b9b-0434-4ad3-8bbc-256055f4146f",
        "class": "vehicle",
        "center": [
          20.456755870448205,
          30.272169519826363,
          -1.2
        ],
        "dimensions": {
          "width": 1.7244759069218274,
          "length": 4.984793463459801,
          "height": 1.6595633070332456
        },
        "yaw": 1.8353163075203032,
        "confidence": 0.9483655947610885
      },
      {
        "id": "1d087566-1a33-469b-89f1-4ecf70bb7da1",
        "class": "vehicle",
        "center": [
          -8.241702674373244,
          29.504849142632963,
          -1.2
        ],
        "dimensions": {
          "width": 1.9308033660961597,
          "length": 4.7325831308664466,
          "height": 1.7204218218434981
        },
        "yaw": -1.7893000137255175,
        "confidence": 0.9391069273050462
      },
      {
        "id": "d9c98317-de60-4706-a942-7e9538e64c4e",
        "class": "vehicle",
        "center": [
          21.70133960890253,
          3.2473912708369426,
          -1.2
        ],
        "dimensions": {
          "width": 1.9165716896872345,
          "length": 4.528591129781088,
          "height": 1.7402061738902472
        },
        "yaw": -0.8802892480526388,
        "confidence": 0.9451060462607955
      },
      {
        "id": "b3c95f08-0483-41ed-b9a7-00a517290a02",
        "class": "vehicle",
        "center": [
          -12.735915735389831,
          -28.455635403455766,
          -1.2
        ],
        "dimensions": {
          "width": 1.6982422972444657,
          "length": 4.430826718154135,
          "height": 1.485417146608401
        },
        "yaw": -2.178969900205442,
        "confidence": 0.8756003137772814
      },
      {
        "id": "2bc5e3b5-631f-4576-8db6-7321b9a1ac10",
        "class": "vehicle",
        "center": [
          12.144410020668687,
          36.185859118872955,
          -1.2
        ],
        "dimensions": {
          "width": 1.6820645037242676,
          "length": 4.129494535927563,
          "height": 1.4788461282542458
        },
        "yaw": -0.8839247577917111,
        "confidence": 0.8352470024255975
      },
      {
        "id": "0e080f42-b8ff-4e42-9399-01724684cc38",
        "class": "vehicle",
        "center": [
          5.488263930952627,
          25.548846734800378,
          -1.2
        ],
        "dimensions": {
          "width": 1.99384134938061,
          "length": 4.62872175979841,
          "height": 1.650197600932339
        },
        "yaw": -2.879376283948905,
        "confidence": 0.9397593824886027
      },
      {
        "id": "da9e8150-3c20-461f-9219-fb46d04c713e",
        "class": "vehicle",
        "center": [
          3.2390626493204167,
          -24.473272832989803,
          -1.2
        ],
        "dimensions": {
          "width": 1.9995610841159004,
          "length": 4.711307462332471,
          "height": 1.4125449779729535
        },
        "yaw": 1.9009051355757185,
        "confidence": 0.8809080162409195
      },
      {
        "id": "4b39a281-afe3-4642-a01b-4cafb56e10ce",
        "class": "vehicle",
        "center": [
          -33.43780326762598,
          30.537873215304643,
          -1.2
        ],
        "dimensions": {
          "width": 1.7638845737366977,
          "length": 4.855206528541978,
          "height": 1.423407351405603
        },
        "yaw": -1.1029010818581235,
        "confidence": 0.8855570402747106
      },
      {
        "id": "b00a9a6f-b3c6-410c-8c35-93b37bc58cd6",
        "class": "pedestrian",
        "center": [
          6.7732714939194665,
          36.25025914486068,
          -1.1
        ],
        "dimensions": {
          "width": 0.6264468161490271,
          "length": 0.5839714796550067,
          "height": 1.6217120904244529
        },
        "yaw": 3.096266452422398,
        "confidence": 0.8553315615421
      },
      {
        "id": "22fe542a-3fce-4841-87a1-388c8e9c8216",
        "class": "pedestrian",
        "center": [
          -12.96020638622797,
          18.627272592683184,
          -1.1
        ],
        "dimensions": {
          "width": 0.6733340550006859,
          "length": 0.5439399080885049,
          "height": 1.7447099877762116
        },
        "yaw": -0.14626009740844603,
        "confidence": 0.7879543418353122
      },
      {
        "id": "73a03dfd-b089-49b0-b8bc-d30b528f5328",
        "class": "pedestrian",
        "center": [
          -14.538657077794056,
          33.57023394367013,
          -1.1
        ],
        "dimensions": {
          "width": 0.5392418031974827,
          "length": 0.6251450644788596,
          "height": 1.657452757931013
        },
        "yaw": -0.13281179628225814,
        "confidence": 0.7924481478428481
      },
      {
        "id": "a9165a73-7947-4a8f-a7e3-1a25961c15e3",
        "class": "pedestrian",
        "center": [
          8.98773539866935,
          -6.928374600831077,
          -1.1
        ],
        "dimensions": {
          "width": 0.5702659286855444,
          "length": 0.5883448425230015,
          "height": 1.704766585356432
        },
        "yaw": -2.401121089241811,
        "confidence": 0.9102984157171508
      },
      {
        "id": "ad8b13cd-b465-4405-9e9c-abd4ff903224",
        "class": "pedestrian",
        "center": [
          -19.431257903323925,
          -6.3375557077703135,
          -1.1
        ],
        "dimensions": {
          "width": 0.5389467025932806,
          "length": 0.6236206951334154,
          "height": 1.6977277993172835
        },
        "yaw": 0.6944022432733679,
        "confidence": 0.8298000585346247
      },
      {
        "id": "bed895ad-706d-427e-bd26-4e1c4390f3c4",
        "class": "pedestrian",
        "center": [
          14.403926623144422,
          -16.36809918108846,
          -1.1
        ],
        "dimensions": {
          "width": 0.5492947782150885,
          "length": 0.6997456923079053,
          "height": 1.6325825775405254
        },
        "yaw": 1.644512130810699,
        "confidence": 0.8176888452850761
      },
      {
        "id": "71ca9762-953c-42e9-add9-f2ff8c5f3121",
        "class": "pedestrian",
        "center": [
          13.1748806214867,
          8.232941008820568,
          -1.1
        ],
        "dimensions": {
          "width": 0.5292294527286837,
          "length": 0.6126691145703246,
          "height": 1.838662608112066
        },
        "yaw": -2.976886420281827,
        "confidence": 0.9258542661456803
      },
      {
        "id": "2256c66d-e406-4b6f-b056-172653b963ea",
        "class": "pedestrian",
        "center": [
          19.351508548571367,
          -31.004092970170998,
          -1.1
        ],
        "dimensions": {
          "width": 0.5430746001239382,
          "length": 0.5904557085942822,
          "height": 1.6676712097636348
        },
        "yaw": 2.3409092956464903,
        "confidence": 0.859205645559668
      },
      {
        "id": "5b594efc-f79d-4fc9-97ae-f2faacc7cb1b",
        "class": "pedestrian",
        "center": [
          -33.41978698101485,
          36.34242654412607,
          -1.1
        ],
        "dimensions": {
          "width": 0.5063895456986962,
          "length": 0.5541167409419987,
          "height": 1.6556206542087115
        },
        "yaw": 1.408003191868504,
        "confidence": 0.8494285257821921
      },
      {
        "id": "1cc20e7c-53d3-4898-b9d7-b9e62b073195",
        "class": "pedestrian",
        "center": [
          -26.037452848578624,
          28.62839655819188,
          -1.1
        ],
        "dimensions": {
          "width": 0.6612066307215503,
          "length": 0.5105670950283504,
          "height": 1.7462979416909628
        },
        "yaw": -3.001862870121855,
        "confidence": 0.9087042265840206
      },
      {
        "id": "4053a38f-353b-425f-a956-6542de6032f8",
        "class": "cyclist",
        "center": [
          -7.549622468083108,
          -9.966577851362388,
          -1
        ],
        "dimensions": {
          "width": 0.7654063426349402,
          "length": 1.7999914445829552,
          "height": 1.6352928001652225
        },
        "yaw": 1.9752791550922675,
        "confidence": 0.7404328693929909
      },
      {
        "id": "682b2896-e629-4ea2-864c-fe91faf829fa",
        "class": "cyclist",
        "center": [
          -26.79325660972035,
          36.168216208662656,
          -1
        ],
        "dimensions": {
          "width": 0.6177997780379347,
          "length": 1.866769079692463,
          "height": 1.607641935035771
        },
        "yaw": 0.859872096761257,
        "confidence": 0.7618479286400879
      },
      {
        "id": "aac3394a-00d1-4c45-957b-b2ac26546155",
        "class": "cyclist",
        "center": [
          40.63627810539671,
          1.4156900509971138,
          -1
        ],
        "dimensions": {
          "width": 0.7299524033990029,
          "length": 1.8668665560685953,
          "height": 1.7254744743420662
        },
        "yaw": -3.0979519028682736,
        "confidence": 0.7919938396956541
      },
      {
        "id": "7619bcd4-a666-4db0-bdee-cb9a2894c93b",
        "class": "cyclist",
        "center": [
          -31.853405013644494,
          34.397870116066485,
          -1
        ],
        "dimensions": {
          "width": 0.7926647471114824,
          "length": 1.724324338920852,
          "height": 1.7815732826372626
        },
        "yaw": 1.6279769966317055,
        "confidence": 0.7312665057563723
      }
    ]
  },
  "metadata": {
    "vehicleCount": 8,
    "pedestrianCount": 10,
    "cyclistCount": 4,
    "complexity": "high",
    "optimalBranch": "AGILE3D_CP_Pillar_032"
  }
}